viewer/__init__.py
browsable-0.0.1.dist-info/METADATA
browsable-0.0.1.dist-info/WHEEL
browsable-0.0.1.dist-info/top_level.txt
browsable-0.0.1.dist-info/RECORD
